setup.py
ahkab/__init__.py
ahkab/__main__.py
ahkab/__version__.py
ahkab/ac.py
ahkab/ahkab.py
ahkab/bfpss.py
ahkab/circuit.py
ahkab/compile.py
ahkab/constants.py
ahkab/csvlib.py
ahkab/custom.py
ahkab/dc_analysis.py
ahkab/dc_guess.py
ahkab/devices.py
ahkab/diode.py
ahkab/ekv.py
ahkab/fourier.py
ahkab/gear.py
ahkab/implicit_euler.py
ahkab/mdn.py
ahkab/mosq.py
ahkab/netlist_parser.py
ahkab/options.py
ahkab/plotting.py
ahkab/printing.py
ahkab/pss.py
ahkab/py3compat.py
ahkab/pz.py
ahkab/results.py
ahkab/shooting.py
ahkab/switch.py
ahkab/symbolic.py
ahkab/testing.py
ahkab/ticker.py
ahkab/time_functions.py
ahkab/transient.py
ahkab/trap.py
ahkab/utilities.py
ahkab.egg-info/PKG-INFO
ahkab.egg-info/SOURCES.txt
ahkab.egg-info/dependency_links.txt
ahkab.egg-info/entry_points.txt
ahkab.egg-info/not-zip-safe
ahkab.egg-info/requires.txt
ahkab.egg-info/top_level.txt