Metadata-Version: 1.1
Name: ahkab
Version: 0.18
Summary: a SPICE-like electronic circuit simulator
Home-page: http://ahkab.github.io/ahkab/
Author: Giuseppe Venturini and others
Author-email: ggventurini+GITHUB@gmail.com
License: GPL
Keywords: electronic circuit simulator numeric symbolic
Platform: UNKNOWN
Classifier: Development Status :: 4 - Beta
Classifier: Intended Audience :: Education
Classifier: Intended Audience :: Science/Research
Classifier: License :: OSI Approved :: GNU General Public License (GPL)
Classifier: Operating System :: POSIX
Classifier: Operating System :: POSIX :: Linux
Classifier: Operating System :: Microsoft :: Windows
Classifier: Operating System :: MacOS
Classifier: Natural Language :: English
Classifier: Programming Language :: Python :: 2
Classifier: Programming Language :: Python :: 2.7
Classifier: Programming Language :: Python :: 3
Classifier: Programming Language :: Python :: 3.4
